{
    "data": {
        "wiki": [
            {
                "datetime": "2022年07月23日 11時の問題",
                "url": "https://ja.wikipedia.org/?curid=2424818",
                "title": "鹿嶋神社 (品川区)",
                "text": "〇〇は、東京都品川区大井に鎮座する神社である。『新編武蔵風土記稿』には鹿島社（かしましゃ）、『江戸名所図会』には鹿島大明神社（かしまだいみょうじんじゃ）として紹介された。また、地名から俗に大井鹿嶋神社とも称される。"
            },
            {
                "datetime": "2022年07月23日 08時の問題",
                "url": "https://ja.wikipedia.org/?curid=2935063",
                "title": "サッカーサバ島代表",
                "text": "〇〇は、サバ島サッカー協会により編成されるサバ島のサッカーのナショナルチームである。サバ島代表は、FIFA及び、CONCACAFに加盟していないため、ワールドカップ、CONCACAFゴールドカップに参加できず、他のチームとの対戦も、国際Aマッチとは認められない。また、オランダサッカー協会の援助も受けていない。シント・ユースタティウス島と2004年,2006年に試合を行い、2敗1分けと初勝利を挙げる事はできなかった。"
            },
            {
                "datetime": "2022年07月23日 07時の問題",
                "url": "https://ja.wikipedia.org/?curid=1164528",
                "title": "めっちぇん",
                "text": "〇〇は、サンミュージックプロダクションに所属していた日本のお笑いコンビ。結成は2007年2月、2010年9月10日解散。事務所のプロフィールも削除されており、引退した模様。"
            },
            {
                "datetime": "2022年07月23日 06時の問題",
                "url": "https://ja.wikipedia.org/?curid=3899931",
                "title": "ダッグバーティ・ラーマナイドゥ",
                "text": "〇〇は、インドの映画プロデューサー、政治家。映画製作会社スレーシュ・プロダクションの創設者であり、生涯で13言語150本以上の映画を製作したことで「世界で最も多くの映画を製作した映画プロデューサー」としてギネス世界記録に登録されている。1999年から2004年にかけてグントゥール県選出のローク・サバー議員を務めていた。2012年にインド映画への貢献を認められパドマ・ブーシャン勲章を授与された。2009年にインド映画の最高賞ダーダーサーハバ・パールケー賞を受賞し、テルグ語映画での活動からラグパティ・ヴェンカイアー賞、フィルムフェア賞 南インド映画部門 生涯功労賞を受賞している。1991年に「ラーマナイドゥ慈善信託」を設立し、同団体を通じて収入の大半を慈善活動のために使用していた。"
            },
            {
                "datetime": "2022年07月23日 05時の問題",
                "url": "https://ja.wikipedia.org/?curid=371207",
                "title": "能福寺",
                "text": "〇〇は、兵庫県神戸市兵庫区にある天台宗の寺院。山号は宝積山。本尊は阿弥陀如来。兵庫大仏で有名。ビルシャナ殿は新西国三十三箇所第23番札所で本尊は十一面観音である。"
            },
            {
                "datetime": "2022年07月23日 04時の問題",
                "url": "https://ja.wikipedia.org/?curid=3957744",
                "title": "正寿院",
                "text": "〇〇は、以下の寺院や人物などの院号。"
            },
            {
                "datetime": "2022年07月23日 03時の問題",
                "url": "https://ja.wikipedia.org/?curid=3312366",
                "title": "T・J・マコーネル",
                "text": "〇〇は、アメリカ合衆国・ペンシルベニア州ピッツバーグ出身のプロバスケットボール選手。NBAのインディアナ・ペイサーズに所属している。ポジションはポイントカード。"
            },
            {
                "datetime": "2022年07月23日 02時の問題",
                "url": "https://ja.wikipedia.org/?curid=2022939",
                "title": "乙 (漫画家)",
                "text": "〇〇は、MOROHA）は、日本の漫画家。主に商業誌で成人向け漫画を執筆している。「乙（もろは）」と表記されることが多い。現在は「二式鋏（にしきばさみ）」名義で、電子コミック「コミックハウスEroha」にて連載中。"
            },
            {
                "datetime": "2022年07月23日 01時の問題",
                "url": "https://ja.wikipedia.org/?curid=1242327",
                "title": "ウィーン国際園芸博覧会 (1974年)",
                "text": "〇〇は、1974年4月18日から10月14日までオーストリアのウィーンで開催された国際園芸博覧会であり、博覧会国際事務局が認定した国際博覧会（特別博）である。会期中260万人が来場した。"
            },
            {
                "datetime": "2022年07月23日 00時の問題",
                "url": "https://ja.wikipedia.org/?curid=1629380",
                "title": "高倉一朗",
                "text": "〇〇は、日本の歌手。本名は石倉 寛章。レコード会社は日本クラウン。血液型はAB型。"
            },
            {
                "datetime": "2022年07月22日 23時の問題",
                "url": "https://ja.wikipedia.org/?curid=4422526",
                "title": "乾州",
                "text": "〇〇は、中国にかつて存在した州。唐代から民国初年にかけて、現在の陝西省咸陽市南西部に設置された。"
            },
            {
                "datetime": "2022年07月22日 22時の問題",
                "url": "https://ja.wikipedia.org/?curid=1490345",
                "title": "川島蹴太",
                "text": "〇〇は、日本のミュージシャン。作詞・作曲家、ボーカリスト、ギタリスト、音楽プロデューサーとして活動している。愛知県名古屋市出身。血液型AB型。従兄弟はジャズミュージシャンで音楽・映像プロデューサーのヒロ川島。"
            },
            {
                "datetime": "2022年07月22日 21時の問題",
                "url": "https://ja.wikipedia.org/?curid=77837",
                "title": "NHK前橋放送局",
                "text": "〇〇は、群馬県を放送対象地域とする日本放送協会（NHK）の地域放送局。総合テレビとFM放送で県域放送を行っている。NHK教育テレビとAM放送（ラジオ第1放送・ラジオ第2放送）については関東広域圏扱いとして、管轄の東京本局からカバー・中継されている。"
            },
            {
                "datetime": "2022年07月22日 20時の問題",
                "url": "https://ja.wikipedia.org/?curid=2497243",
                "title": "小野瀬康介",
                "text": "〇〇は、東京都大田区出身のプロサッカー選手。Jリーグ・ガンバ大阪所属。ポジションはミッドフィールダー。"
            },
            {
                "datetime": "2022年07月22日 19時の問題",
                "url": "https://ja.wikipedia.org/?curid=449995",
                "title": "福島正守",
                "text": "〇〇は、正鎮と共に誉田の戦い、道明寺の戦いに参加。天王寺・岡山の戦いの最終決戦では、茶臼山西部隊2500人の一員として、徳川勢と戦いを繰り広げた。大坂の陣の後の消息は不明。子孫を名乗る家がある。"
            },
            {
                "datetime": "2022年07月22日 18時の問題",
                "url": "https://ja.wikipedia.org/?curid=1281702",
                "title": "九三式側車付自動二輪車",
                "text": "〇〇は、日本陸軍で使用されていた側車付自動二輪車の制式名である。同車両は米国ハーレーダビッドソン社の製品に一部の改良を加えたもので、既に陸軍が採用していた同社製の側車付自動二輪車と酷似していた。"
            },
            {
                "datetime": "2022年07月22日 17時の問題",
                "url": "https://ja.wikipedia.org/?curid=1943824",
                "title": "タマコウォルズ",
                "text": "〇〇は、日本のロックバンド。2005年結成。「マダラ紛争」や「六角マルマル綺譚」などのイベントを行う。初期のCDはライブ会場で販売。"
            },
            {
                "datetime": "2022年07月22日 16時の問題",
                "url": "https://ja.wikipedia.org/?curid=4396910",
                "title": "金淳興",
                "text": "〇〇は、日本統治時代の朝鮮および大韓民国の資本家。日本統治時代の親日派すなわち1945年以前の朝鮮半島における日本帝国主義の政策・支配に協力した反朝鮮民族的な人物とされる。"
            },
            {
                "datetime": "2022年07月22日 15時の問題",
                "url": "https://ja.wikipedia.org/?curid=2813545",
                "title": "ロクマリアケール",
                "text": "〇〇は、フランス、ブルターニュ地域圏、モルビアン県のコミューン。"
            },
            {
                "datetime": "2022年07月22日 14時の問題",
                "url": "https://ja.wikipedia.org/?curid=1084521",
                "title": "容閎",
                "text": "〇〇は、清末の政治改革者・実業家。近代中国史上初のアメリカ合衆国への留学生である。"
            },
            {
                "datetime": "2022年07月22日 13時の問題",
                "url": "https://ja.wikipedia.org/?curid=72916",
                "title": "岩宿駅",
                "text": "〇〇は、群馬県みどり市笠懸町阿左美にある、東日本旅客鉄道（JR東日本）両毛線の駅である。"
            },
            {
                "datetime": "2022年07月22日 11時の問題",
                "url": "https://ja.wikipedia.org/?curid=3409071",
                "title": "めぶきフィナンシャルグループ",
                "text": "〇〇は、足利ホールディングスと常陽銀行の経営統合により誕生した金融持株会社。"
            },
            {
                "datetime": "2022年07月22日 08時の問題",
                "url": "https://ja.wikipedia.org/?curid=419087",
                "title": "いろは丸展示館",
                "text": "〇〇は、広島県福山市鞆町にある、備後灘で1867年5月26日に起こったいろは丸と明光丸の衝突事件の概要を展示する博物館である。1989年（平成元年）7月に開設された。"
            },
            {
                "datetime": "2022年07月22日 07時の問題",
                "url": "https://ja.wikipedia.org/?curid=909185",
                "title": "Informix",
                "text": "〇〇は、かつてアメリカ合衆国にあったソフトウェア企業である。関係データベース管理システム (RDBMS) 製品群〇〇を開発したが、経営不振により2001年にIBMに買収された。"
            },
            {
                "datetime": "2022年07月22日 06時の問題",
                "url": "https://ja.wikipedia.org/?curid=2495512",
                "title": "フリッツラー",
                "text": "〇〇は、ドイツ連邦共和国ヘッセン州北部のシュヴァルム＝エーダー郡に属す小都市で、同郡の経済的中心地である。この街は、ドイツ中部および北部のキリスト教化（723年の聖ボニファティウスによるドナーアイヒェの伐採）ならびに中世の神聖ローマ帝国（919年の帝国会議でハインリヒ1世が東フランク王に選出された）の起点となった聖堂と皇帝の街である。〇〇の名前は元々は「平和の街」を意味する Friedeslar に由来する。"
            },
            {
                "datetime": "2022年07月22日 05時の問題",
                "url": "https://ja.wikipedia.org/?curid=3636240",
                "title": "サント＝ジャンヌ＝ダルク",
                "text": "〇〇は、フランス語の地名、教会名。1920年に列福されたジャンヌ・ダルクにちなむ。"
            },
            {
                "datetime": "2022年07月22日 04時の問題",
                "url": "https://ja.wikipedia.org/?curid=658311",
                "title": "松岬神社",
                "text": "〇〇は、山形県米沢市に鎮座する神社。上杉神社の摂社。松が岬公園（米沢城址）に位置し、上杉鷹山、上杉景勝、直江兼続、細井平洲、竹俣当綱、莅戸善政を祀る。"
            },
            {
                "datetime": "2022年07月22日 03時の問題",
                "url": "https://ja.wikipedia.org/?curid=4378105",
                "title": "THE 仲井戸麗市 BOOK",
                "text": "〇〇は、1985年8月31日に発表された仲井戸麗市の1stアルバム。"
            },
            {
                "datetime": "2022年07月22日 02時の問題",
                "url": "https://ja.wikipedia.org/?curid=4406950",
                "title": "Let Me Fly 〜その未来へ〜",
                "text": "〇〇は、PRODUCE 101 JAPAN SEASON2の楽曲である。2021年3月30日に配信。"
            },
            {
                "datetime": "2022年07月22日 01時の問題",
                "url": "https://ja.wikipedia.org/?curid=69433",
                "title": "文字禍",
                "text": "〇〇は、中島敦の短編小説（掌編小説）。1942年（昭和17年）に発表された中島のデビュー作の一つである。アッシリアの碩学ナブ・アヘ・エリバ博士が、文字の霊が人間に及ぼす災いについて研究し、アッシュールバニパル王に進言するものの認められず、最後には文字の霊の呪いによって書物（粘土板）の下敷きとなり圧死してしまうという物語である。初出時は、他1篇「山月記」と共に「古譚」の題名で総括され、深田久弥の推薦により『文學界』1942年2月号に掲載された。同年7月に筑摩書房から刊行された単行本『光と風と夢』に収録された際には、「山月記」「狐憑」「木乃伊」と合わせた連作「古譚」として収録された。"
            },
            {
                "datetime": "2022年07月22日 00時の問題",
                "url": "https://ja.wikipedia.org/?curid=3564691",
                "title": "みゆはん",
                "text": "〇〇は、日本のシンガーソングライター、声優。香川県出身。株式会社クラウドナイン所属。身長154cm、血液型はA型。2017年2月22日にミニアルバム「自己スキーマ」でビクターエンタテインメントからメジャーデビューした。"
            },
            {
                "datetime": "2022年07月21日 23時の問題",
                "url": "https://ja.wikipedia.org/?curid=4017241",
                "title": "くもりときどきミートボールシリーズ",
                "text": "〇〇は、2006年公開のソニー・ピクチャーズ アニメーション製作による『くもりときどきミートボール』（Cloudy with a Chance of Meatballs）から始まる作品群である。"
            },
            {
                "datetime": "2022年07月21日 22時の問題",
                "url": "https://ja.wikipedia.org/?curid=730972",
                "title": "厚東氏",
                "text": "〇〇は、日本の氏族のひとつ。長門を本拠とした豪族、長門守護。本姓は物部氏。支族として11代当主武時の三男を祖とする秋吉氏などがある。"
            },
            {
                "datetime": "2022年07月21日 21時の問題",
                "url": "https://ja.wikipedia.org/?curid=4245239",
                "title": "ROAD59 -新時代任侠特区-",
                "text": "〇〇は、ブシロードによるメディアミックスプロジェクト。"
            },
            {
                "datetime": "2022年07月21日 20時の問題",
                "url": "https://ja.wikipedia.org/?curid=417473",
                "title": "堺区",
                "text": "〇〇は、堺市を構成する7行政区のうちの1つ。中世以来の環濠都市であった地域を含み、市役所、裁判所などの官庁やシティホテル、商店などが集積している堺市都心部の機能が集積した中心部である。"
            },
            {
                "datetime": "2022年07月21日 19時の問題",
                "url": "https://ja.wikipedia.org/?curid=1122402",
                "title": "根雪",
                "text": "〇〇は、冬のあいだ積雪状態が続くことを指す用語である。気象庁では長期積雪と呼ぶ。一般的には、主に降雪量の多い雪国や降水量が少ない寒冷地で雪が降り積もった後に雪融けの季節まで雪が地面を覆う(つまり積雪)状態が続くことを、その始まりや終わりを指して「〇〇が張る」「〇〇が解ける」などと呼び、冬の訪れや春の訪れの時期をつかさどる為に使われている。気象庁の用語においては、一旦積雪が消失しても、積雪期間がある条件を満たせば、再び積雪した際も長期積雪が継続しているとみなされる(後述)。"
            },
            {
                "datetime": "2022年07月21日 18時の問題",
                "url": "https://ja.wikipedia.org/?curid=1310985",
                "title": "エッピンゲン",
                "text": "〇〇は、ドイツ連邦共和国バーデン＝ヴュルテンベルク州北西部の都市。ハイルブロンの西約22km、カールスルーエの北東約41kmに位置する。この都市は、ハイルブロンを上級中心とするハイルブロン＝フランケン地域連合のハイルブロンを中心とする中級地域圏に含まれる。〇〇は、ネッカーズルムに次ぐハイルブロン郡第2の都市であり、2002年1月1日から大規模郡都市となっている。"
            },
            {
                "datetime": "2022年07月21日 17時の問題",
                "url": "https://ja.wikipedia.org/?curid=2945162",
                "title": "ポルシェ・マカン",
                "text": "〇〇は、インドネシア語でトラを意味する。"
            },
            {
                "datetime": "2022年07月21日 16時の問題",
                "url": "https://ja.wikipedia.org/?curid=1038844",
                "title": "愛の秘密",
                "text": "〇〇は、1976年5月10日～7月2日にTBS「花王 愛の劇場」枠にて放送された昼ドラマである。"
            },
            {
                "datetime": "2022年07月21日 15時の問題",
                "url": "https://ja.wikipedia.org/?curid=3010452",
                "title": "形象物",
                "text": "〇〇は、昼間において水上を航海中（航行中に加え、錨泊中、岸壁係留中、乗揚げ（座礁）の状態も含まれる）の船舶のマストに、他船に識別できるように掲げられた標示物のことである。"
            }
        ]
    }
}