{
    "data": {
        "wiki": [
            {
                "url": "https://ja.wikipedia.org/?curid=276331",
                "title": "市川大祐",
                "text": "〇〇は、静岡県清水市（現・静岡市清水区）出身の元サッカー選手。ポジションはディフェンダー。日本代表にも選出され、2002 FIFAワールドカップに出場した。「17歳322日」という日本代表最年少出場記録を持つ（2019年時点）。"
            },
            {
                "url": "https://ja.wikipedia.org/?curid=2468691",
                "title": "万年山古墳",
                "text": "〇〇は、大阪府枚方市枚方上之町に所在した前方後円墳であった可能性が推定される古墳。1904年（明治37年）に銅鏡8面が出土して、古墳の存在が明らかとなった。万年寺山古墳（まんねんじやまこふん）ともいう。"
            },
            {
                "url": "https://ja.wikipedia.org/?curid=3592108",
                "title": "ストラー数",
                "text": "〇〇は、分岐複雑度の数値尺度である。これらの数は、Robert E. Horton (1945) と Arthur Newell Strahler (1952, 1957) によって、水文学で発展した。この応用において、彼らはストラー河川次数 (strahler stream order) と見なされ、支線の階層に基づいたストリームサイズを定義するのに使用される。彼らは、L-systems および (生物学的) 木および動物の呼吸器、循環器および階層的生物学的構造の分析において、また、高水準言語のコンパイルのためのレジスタ割り付け、およびソーシャルネットワーク分析において生じる。代替の河川次数の系 (stream order systems) は、Shreve と Hodgkinson らによって発展した。〇〇および shreve 系の統計的比較、流れ/リンク長の分析とともに、Smart によって与えられている。"
            },
            {
                "url": "https://ja.wikipedia.org/?curid=113138",
                "title": "FOCUS",
                "text": "〇〇は、1981年10月23日に新潮社から創刊された写真週刊誌の草分け。2001年休刊。取締役の編集者斉藤十一が、創刊に多く関係した。"
            },
            {
                "url": "https://ja.wikipedia.org/?curid=3521441",
                "title": "1981年の阪神タイガース",
                "text": "〇〇は、〇〇の動向をまとめる。この年の阪神タイガースは、中西太監督の2年目のシーズン（途中就任の前年を含む）である。"
            },
            {
                "url": "https://ja.wikipedia.org/?curid=132438",
                "title": "阪神5311形電車",
                "text": "〇〇は、阪神電気鉄道が所有していた、各駅停車用の通勤形電車である。普通運用の4連化に伴い、1両走行が可能な増結用車両を増強するため、1968年から1969年にかけて4両が製造された。"
            },
            {
                "url": "https://ja.wikipedia.org/?curid=1186660",
                "title": "フード・プラネット",
                "text": "〇〇は、かつて札幌市中央区に本社を置いていた日本の企業である。"
            },
            {
                "url": "https://ja.wikipedia.org/?curid=2230456",
                "title": "アルゼンティニアン・ヘアレス・ドッグ",
                "text": "〇〇は、アルゼンチンのブエノスアイレス原産のヘアレス犬種のひとつである。別名はピラ・ドッグ（英：Pila Dog）など。"
            },
            {
                "url": "https://ja.wikipedia.org/?curid=197797",
                "title": "ストリップ・ポーカー",
                "text": "〇〇は、ポーカーにプレーヤー（対戦相手あるいは自身）による脱衣を組み込んだ宴会ゲーム。〇〇には、参加プレーヤー数や規則に関する公式の定義は存在しない。また、普及を推進する団体もないとされる。どのようなゲームであっても脱衣さえルールに含まれていれば、〇〇たりえる。一般的には、ポーカーに負けると服を脱ぎ、全裸になると負け（家庭用ゲーム機やテレビ番組の場合は下着まで）というのが多い。"
            },
            {
                "url": "https://ja.wikipedia.org/?curid=3484613",
                "title": "アーティレリー",
                "text": "〇〇は、デンマーク出身のスラッシュメタル・バンド。デンマーク産スラッシュの先駆者であり、母国を代表する古参のヘヴィメタル・グループとして知られる。"
            },
            {
                "url": "https://ja.wikipedia.org/?curid=183645",
                "title": "第一次ブルガリア帝国",
                "text": "〇〇は、7世紀より11世紀前半まで続いた東ヨーロッパのブルガリアに栄えた帝国。10世紀前半におけるシメオン1世の治世に全盛期を迎えたが、東ローマ帝国によって滅ぼされた。"
            },
            {
                "url": "https://ja.wikipedia.org/?curid=1490517",
                "title": "藤栄道彦",
                "text": "〇〇は、日本の漫画家。栃木県宇都宮市出身。男性。B型。那智正芳（なち まさよし）名義で描いていたこともあった。名字の読みを長らく「とうえい」としていたが、2020年10月頃より「ふじえい」と名乗っている。"
            },
            {
                "url": "https://ja.wikipedia.org/?curid=2517036",
                "title": "サンファーレ",
                "text": "〇〇は、三重県桑名市桑栄町の再開発地区で複合商業施設である。"
            },
            {
                "url": "https://ja.wikipedia.org/?curid=1998528",
                "title": "ポートランド都市圏",
                "text": "〇〇は、アメリカ合衆国オレゴン州ポートランド市を中心としたオレゴン州とワシントン州にまたがる都市圏である。ポートランド大都市圏（英: Portland metropolitan area）や大ポートランド（英: Greater Portland）とも呼ばれる。アメリカ合衆国国勢調査局はポートランド＝バンクーバー大都市統計地域の範囲を、オレゴン州クラカマス郡、コロンビア郡、マルトノマ郡、ワシントン郡、ヤムヒル郡、およびワシントン州クラーク郡、スカマニア郡の全域として定義している。ワシントン州の2郡については、オレゴン州とコロンビア川を挟んで離れた位置にある。〇〇のオレゴン州部分は同州最大の都心となっており、地域内の土地利用計画などを行う直接民主制地域政府「メトロ」の管轄下にある。現在の同都市圏の定義は最近になって作られたもので、それ以前はポートランド統合都市圏（英: Portland Consolidated Metropolitan Area）としてセイラム大都市統計地域（英: Salem Metropolitan Statistical Area）を包括する大都市圏を形成していた。もしセイラム都市圏が現在も〇〇の一部に属していたならば、〇〇の人口は2,599,142人になっていた（2008年推定）。さらに近接するロングビュー都市圏も合わせれば人口は2,708,396人にまで上っていた（2008年推定）。"
            },
            {
                "url": "https://ja.wikipedia.org/?curid=549823",
                "title": "ウィーン西駅",
                "text": "〇〇は、オーストリアの首都ウィーンの鉄道駅。"
            },
            {
                "url": "https://ja.wikipedia.org/?curid=663167",
                "title": "粕川サイクリングロード",
                "text": "〇〇は、群馬県伊勢崎市本関町と同市下植木町とを結ぶサイクリングロードである。主に粕川の堤防上を走る。サイクリングロードではあるが、自動車が通行可能な区間が存在する。"
            },
            {
                "url": "https://ja.wikipedia.org/?curid=4302301",
                "title": "大豊産業",
                "text": "〇〇は、香川県高松市に本社を置く、制御・計装機器の販売や保守、電気・通信・土木工事を行う技術商社。主に大手化学工場、石油精製工場、原子力発電所、薬品工場、食品工場、製紙工場などとの取引を主とする。近年はセンシンロボティクスへの出資や畜産業界向けに死亡鶏を検知する自動走行ロボットを自社開発するなど、新規分野への投資を積極的に行なっている。2021年2月22日付で日本治具株式会社の株式を取得し、子会社化。"
            },
            {
                "url": "https://ja.wikipedia.org/?curid=3069039",
                "title": "越阪部豊",
                "text": "〇〇は、埼玉県出身の元プロ野球選手（投手）。"
            },
            {
                "url": "https://ja.wikipedia.org/?curid=730995",
                "title": "スズケン沖縄薬品",
                "text": "〇〇は、沖縄県那覇市に本社を置くスズケングループの一社であり、主として医療用医薬品の卸売を営む会社である。"
            },
            {
                "url": "https://ja.wikipedia.org/?curid=2608091",
                "title": "須永恆雄",
                "text": "〇〇は、ドイツ文学者、明治大学名誉教授。"
            },
            {
                "url": "https://ja.wikipedia.org/?curid=1875337",
                "title": "高千代酒造",
                "text": "〇〇は、新潟県南魚沼市長崎に本社を置く酒蔵である。"
            },
            {
                "url": "https://ja.wikipedia.org/?curid=1620533",
                "title": "中村神社",
                "text": "〇〇は、石川県金沢市中村町にある神社。祭神は、武甕槌命・経津主神・天児屋根命・比咩大神。"
            },
            {
                "url": "https://ja.wikipedia.org/?curid=2297202",
                "title": "装甲バス",
                "text": "〇〇は、通常、小火器や即席爆発装置から乗客を守るために防護を強化したバスの一種である。"
            },
            {
                "url": "https://ja.wikipedia.org/?curid=896895",
                "title": "果しなき流れの果に",
                "text": "〇〇は、小松左京の長編SF小説。『S-Fマガジン』の1965年2月号から11月号に連載後、単行本として出版、文庫化もされている。誤って『果てしなき流れの果てに』などと表記されることがあるが、題名の「果」には送りがなをつけないのが正しい。"
            },
            {
                "url": "https://ja.wikipedia.org/?curid=3194786",
                "title": "志賀須香村",
                "text": "〇〇は、かつて愛知県碧海郡にあった村である。現在の岡崎市西部（東牧内町・上佐々木町・下佐々木町など）、及び安城市南東部（河野町など）に該当する。"
            },
            {
                "url": "https://ja.wikipedia.org/?curid=546150",
                "title": "学校法人堀越学園 (東京都)",
                "text": "〇〇は、日本の学校法人。1923年4月 - 和洋裁縫女学院（和洋女子大学、和洋九段女子中学校・高等学校の前身）創設者の堀越千代が堀越高等学校の前身となる堀越高等女学校を創立したことから始まる。現在は芸能人やスポーツ選手を多数輩出する堀越高等学校と難関大学合格者を数多く輩出する穎明館中学・高等学校を設置している。群馬県の創造学園大学（廃校）を運営していた同名の学校法人（2013年3月解散）は、創立者が偶然同姓であっただけで、全く無関係の別団体である。"
            },
            {
                "url": "https://ja.wikipedia.org/?curid=2739981",
                "title": "恋花デイズ",
                "text": "〇〇は、オトメイトから2013年6月20日に発売されたPlayStation Portable用女性向け恋愛アドベンチャーゲーム。"
            },
            {
                "url": "https://ja.wikipedia.org/?curid=220672",
                "title": "ヴァンパイア セイヴァー 〜魂の迷い子〜",
                "text": "〇〇は、東まゆみの漫画作品。1997年、エニックス（現スクウェア・エニックス）刊の漫画雑誌『月刊少年ガンガン増刊ガンガンWING』夏季号にて連載開始し、2001年『月刊ガンガンWING』9月号にて連載終了した。ガンガンコミックス全5巻、全24話構成。カプコン開発の2D対戦型格闘ゲーム『ヴァンパイア』シリーズの第3作目『ヴァンパイア セイヴァー The Lord of Vampire』を原作としたファンタジー漫画であるが、アレンジが加えられており、登場人物の性格などは原作ゲームと一致することもあれば、全く異なっている場合もある。また設定としては第2作目『ヴァンパイア ハンター　Darkstalkers' Revenge』に近いキャラクターもいる。ゲーム版『ヴァンパイア』シリーズでプレイヤーが使用できるキャラクターは総勢18人。そのうち、本作に登場するのはパイロンを除く17人。その他に数人のサブキャラクターが登場する。"
            },
            {
                "url": "https://ja.wikipedia.org/?curid=3023042",
                "title": "サイモン・メレルズ",
                "text": "〇〇は、イギリスの俳優。"
            },
            {
                "url": "https://ja.wikipedia.org/?curid=41080",
                "title": "愛知県立看護大学",
                "text": "〇〇は、愛知県名古屋市守山区大字上志段味字東谷に本部を置いていた日本の公立大学である。1995年に設置され、2009年に廃止された。愛知県立看護短期大学が母体。2009年度（平成21年度）には愛知県立大学と統合。"
            },
            {
                "url": "https://ja.wikipedia.org/?curid=1924898",
                "title": "パイセンベルク",
                "text": "〇〇は、ドイツ連邦共和国バイエルン州オーバーバイエルン行政管区のヴァイルハイム＝ショーンガウ郡に属す市場町。この町は1919年までウンター〇〇と称していた。"
            },
            {
                "url": "https://ja.wikipedia.org/?curid=1837530",
                "title": "ニンジャ・アサシン",
                "text": "〇〇は、2009年11月25日に公開されたアメリカ映画（日本公開は2010年）。製作はジョエル・シルバー、ウォシャウスキー兄弟、グラント・ヒル。監督はジェームズ・マクティーグ、主演は韓国の歌手Rain（ピ）。タイトルが示すとおり、忍者がモチーフになっているアクション映画。「アサシン」とは暗殺者のこと。映倫R18+指定。"
            },
            {
                "url": "https://ja.wikipedia.org/?curid=127792",
                "title": "天使十審将",
                "text": "〇〇は、フライト・プラン制作のシミュレーションRPG『BLACK/MATRIX OO』に登場する集団名。プロデヴォン教団を統括する十人の上級幹部の集まりであり、天使長ミトラスをはじめ、臥天使、能天使、法天使、動天使、智天使、力天使、術天使、儀天使、熾天使とそれぞれの役割を持った幹部がいる。"
            },
            {
                "url": "https://ja.wikipedia.org/?curid=2088529",
                "title": "吉田次昭",
                "text": "〇〇は、日本の俳優。本名同じ。旧芸名は吉田 継明。東京都出身。堀越学園卒。オフィスC&P、竹内事務所に所属していた。"
            },
            {
                "url": "https://ja.wikipedia.org/?curid=1116494",
                "title": "鹿児島アリーナ",
                "text": "〇〇は、鹿児島県鹿児島市永吉一丁目にあるスポーツ施設である。鹿児島市が管理している。愛称は2020年4月より西原商会アリーナ。鹿児島刑務所跡に建っており、周辺には多目的広場や公園がある。"
            },
            {
                "url": "https://ja.wikipedia.org/?curid=4145864",
                "title": "藤森亮志",
                "text": "〇〇は、長野県諏訪市出身のサッカー選手。ポジションはミッドフィールダー(MF)。Jリーグ・AC長野パルセイロ所属。"
            },
            {
                "url": "https://ja.wikipedia.org/?curid=1703574",
                "title": "自立生活サポートセンター・もやい",
                "text": "〇〇は、ホームレスや派遣労働者や生活保護受給者などの自立支援を行う団体（認定特定非営利活動法人）。略称はもやい。"
            },
            {
                "url": "https://ja.wikipedia.org/?curid=3035961",
                "title": "海馬島 (歯舞群島)",
                "text": "〇〇は、歯舞諸島の島のひとつ。多楽島の南東に位置し、北海道からは37キロメートル離れている。戦前は日本が統治していた島であったが、1945年のソ連対日参戦の結果ソ連により占領される。ソビエト連邦の崩壊以降はロシア連邦が実効支配し、ロシアの行政区画においてはサハリン州南クリル都市管区（2006年までは管区）に属している。しかし日本政府はソ連による占領以降も「北方領土」の一部として領有権を主張しており、日本の行政区画においては1959年まで歯舞村に所属し、同年以降は根室市に属している。"
            },
            {
                "url": "https://ja.wikipedia.org/?curid=3625312",
                "title": "語部マサユキ",
                "text": "〇〇は、日本の小説家、ライトノベル作家。"
            },
            {
                "url": "https://ja.wikipedia.org/?curid=3322715",
                "title": "フランツ・ファン・バルコム",
                "text": "〇〇は、オランダのサッカー選手・サッカー指導者。"
            }
        ]
    }
}